pbpl_warpx/__init__.py
pbpl_warpx/_version.py
pbpl_warpx/_version.pyi
pbpl_warpx/py.typed
pbpl_warpx-1.2.dist-info/METADATA
pbpl_warpx-1.2.dist-info/WHEEL
pbpl_warpx-1.2.dist-info/licenses/LICENSE
pbpl_warpx-1.2.dist-info/RECORD
